Metadata-Version: 2.1
Name: borgssh
Version: 0.4.21
Summary: A package to simplify the borgbackup use with a borg server
Home-page: https://gitlab.com/jaromrax/sshborg
Author: me
Author-email: mail@gmail.com
License: GPL2
Platform: UNKNOWN
